{
	"attributes": 	{
		"Id" : 300100050996877,
		"ObjectVersionNumber" : 13,
		"ProposedStartDate" : "2015-01-14T00:00:00-0800",
		"ProposedFinishDate" : null,
		"PercentComplete" : 0,
		"Priority" : null,
		"ResourceId" : 300100024326751,
		"ProjectId" : 300100025403953,
		"ProjElementId" : 300100050996878,
		"ElementVersionId" : 300100050996876,
		"PlanVersionId" : 300100025403959,
		"PlanStatusCode" : "WORKING",
		"PlanVersionId1" : 300100025403959,
		"ProjectId1" : 300100025403953,
		"ProjectName" : "QA_TMDB_Project",
		"LastUpdateDate" : "2015-01-30T15:33:23-0800",
		"LastUpdateLogin" : "10E152BEFADB434AE0530803F00AE6AF",
		"LastUpdatedBy" : "Connor.Horton",
		"CreatedBy" : "Connor.Horton",
		"CreationDate" : "2015-01-26T16:23:18-0800",
		"DisplayName" : "Abraham Mason",
		"ResourceId1" : 300100024326751,
		"Description" : null,
		"StructureType" : "FIN_EXEC",
		"TaskName" : "test13",
		"IssueId" : null,
		"DenormParentElementId" : 300100025403958,
		"SessionResourceId" : 300100024326655,
		"TaskHierarchy" : "QA_TMDB_Project",
		"IssueSummary" : null,
		"CreatedByDisplayName" : "Connor Horton",
		"LastUpdateDate1" : "2015-03-09T13:07:50-0700",
		"HistoryColumn" : "2015-03-09T13:07:50-0700",
		"showMarkAsStartedBtn" : "true",
		"ProgressStatusCode" : "NOT_STARTED",
		"ObjectVersionNumber1" : 14,
		"ProgressEnteredDate" : "2015-01-26T00:00:00-0800",
		"showMarkAsFinishedBtn" : "false",
		"IsStartDateExist" : "true",
		"IsFinishDateExist" : "false",
		"ProjElementId1" : 300100050996878,
		"NumberOfExceptions" : 1,
		"HealthStsCode" : "ON_TRACK",
		"ItdQuantity" : 0,
		"Quantity" : null,
		"StartDate" : "2015-01-14T00:00:00-0800",
		"FinishDate" : null,
		"ProposedQuantity" : null,
		"MilestoneFlag" : "N",
		"ResourceId2" : 300100024326655,
		"TaskFollowerId" : 300100051024892,
		"ObjectVersionNumber2" : 1,
		"ElementVersionId1" : 300100050996876,
		"ShowReadOnlyProject" : "yes",
		"ShowIssueSummary" : "no",
		"ShowReadOnlyStartDate" : "no",
		"ShowReadOnlyFinishDate" : "no",
		"ShowReadOnlyPriority" : "no",
		"HidePercentComplete" : "no",
		"ShowEditableOwnerLov" : "yes",
		"ShowExceptions" : "yes",
		"Exceptions" : "The planned start date for this task has already passed.\n",
		"osnPlanLineId" : 300100050996877,
		"Followers" : "Connor Horton\n",
		"ShowFollowers" : "yes",
		"TaskFollowerDisplayName" : "",
		"TaskFollowerResourceId" : null
	},
	"links": {
"self":{"href":"/pjlFollowedTasks/300100050996877","rel":"/linkRelations/common/self"}
	}
}
