{
	"attributes": 	{
		"Id" : 300100026789902,
		"ObjectVersionNumber" : 2,
		"ProposedStartDate" : "2012-01-01T00:00:00-0800",
		"ProposedFinishDate" : null,
		"PercentComplete" : null,
		"Priority" : null,
		"DisplayName" : "Connor Horton",
		"Description" : null,
		"ResourceId" : 300100024326655,
		"ResourceId1" : 300100024326655,
		"ProjectId" : 300100026789891,
		"ProjElementId" : 300100026789903,
		"ElementVersionId" : 300100026789901,
		"PlanVersionId" : 300100026789896,
		"PlanStatusCode" : "WORKING",
		"PlanVersionId1" : 300100026789896,
		"ProjectId1" : 300100026789891,
		"ProjectName" : "QA_PJE_RRF_DEL_PROJECT",
		"ProjectCategory" : "FIN_EXEC",
		"TaskName" : "QA_PJE_RRF_DEL_TASK2",
		"SessionResourceId" : 300100024326655,
		"CreatedBy" : "Abraham.Mason",
		"CreationDate" : "2013-08-21T20:52:40-0700",
		"LastUpdateDate" : "2013-08-21T21:13:57-0700",
		"LastUpdatedBy" : "Abraham.Mason",
		"LastUpdateLogin" : "E480C44D9A53488DE0435360F00A79BE",
		"DenormParentElementId" : 300100026789895,
		"IssueId" : null,
		"IssueSummary" : null,
		"StructureType" : "FIN_EXEC",
		"TaskHierarchy" : "QA_PJE_RRF_DEL_PROJECT",
		"CreatedByDisplayName" : "Abraham Mason",
		"HistoryColumn" : "2013-08-21T21:13:57-0700",
		"LastUpdateDate1" : "2013-08-21T21:13:57-0700",
		"ProgressStatusCode" : "NOT_STARTED",
		"ProgressEnteredDate" : null,
		"showMarkAsFinishedBtn" : "false",
		"showMarkAsStartedBtn" : "true",
		"IsFinishDateExist" : "false",
		"IsStartDateExist" : "true",
		"FinishDate" : null,
		"HealthStsCode" : "ON_TRACK",
		"ItdQuantity" : 0,
		"MilestoneFlag" : "N",
		"NumberOfExceptions" : null,
		"ObjectVersionNumber1" : 2,
		"ProjElementId1" : 300100026789903,
		"ProposedQuantity" : null,
		"Quantity" : null,
		"StartDate" : "2012-01-01T00:00:00-0800",
		"SyncProjectId" : null,
		"ProposedResAllocation" : 100,
		"IsProjectLOVUpdateable" : null,
		"TransProposedFinishDate" : "1970-01-01T00:00:00-0800",
		"ReadOnlyProjectName" : "QA_PJE_RRF_DEL_PROJECT",
		"ReadOnlyProposedFinishDate" : null,
		"ReadOnlyProposedStartDate" : "2012-01-01T00:00:00-0800",
		"PrimaryResourceId" : 300100024326655,
		"ReadOnlyPriority" : null,
		"ReadOnlyDisplayName" : "Connor Horton",
		"ShowExceptions" : "yes",
		"Exceptions" : "The planned start date for this task has already passed.\n",
		"ShowReadOnlyProject" : "yes",
		"ShowIssueSummary" : "no",
		"ShowReadOnlyStartDate" : "no",
		"ShowReadOnlyFinishDate" : "no",
		"ShowReadOnlyPriority" : "no",
		"HidePercentComplete" : "no",
		"ShowEditableOwnerLov" : "yes",
		"IsProjectLOVUpdatable" : false,
		"osnPlanLineId" : 300100026789902,
		"TaskFollowerDisplayName" : "",
		"TaskFollowerResourceId" : null
	},
	"links": {
"self":{"href":"/pjlMyTasks/300100026789902","rel":"/linkRelations/common/self"}
,
"update":{"href":"/pjlMyTasks/300100026789902","rel":"/linkRelations/pjlMyTask/update"}
,
"markAsStarted":{"href":"/pjlMyTasks/300100026789902?action=markAsStarted&isStartDateExist=true&isFinishDateExist=false","rel":"/linkRelations/pjlMyTask/update"}
,
"details":{"href":"/pjlMyTasks/300100026789902","rel":"/linkRelations/pjlMyTask/details"}
,
"markAsFinished":{"href":"/pjlMyTasks/300100026789902?action=markAsFinished&isStartDateExist=true&isFinishDateExist=false","rel":"/linkRelations/pjlMyTask/update"}
	}
}
